flatjson/__init__.py
flatjson-0.1.1.dist-info/WHEEL
flatjson-0.1.1.dist-info/METADATA
flatjson-0.1.1.dist-info/RECORD
